.coveragerc
.testr.conf
AUTHORS
ChangeLog
HACKING.rst
LICENSE
MANIFEST.in
README.rst
babel.cfg
openstack-common.conf
requirements.txt
run_tests.sh
setup.cfg
setup.py
test-requirements.txt
tox.ini
apic_ml2/__init__.py
apic_ml2/neutron/__init__.py
apic_ml2/neutron/agent/__init__.py
apic_ml2/neutron/agent/linux/__init__.py
apic_ml2/neutron/agent/linux/apic_dhcp.py
apic_ml2/neutron/agent/metadata/__init__.py
apic_ml2/neutron/agent/metadata/namespace_proxy.py
apic_ml2/neutron/db/__init__.py
apic_ml2/neutron/db/port_ha_ipaddress_binding.py
apic_ml2/neutron/db/migration/__init__.py
apic_ml2/neutron/db/migration/alembic.ini
apic_ml2/neutron/db/migration/cli.py
apic_ml2/neutron/db/migration/alembic_migrations/README
apic_ml2/neutron/db/migration/alembic_migrations/__init__.py
apic_ml2/neutron/db/migration/alembic_migrations/env.py
apic_ml2/neutron/db/migration/alembic_migrations/script.py.mako
apic_ml2/neutron/db/migration/alembic_migrations/versions/4c0c1e2c0160_ha_ip_address_to_port_id_association.py
apic_ml2/neutron/db/migration/alembic_migrations/versions/HEAD
apic_ml2/neutron/db/migration/alembic_migrations/versions/README
apic_ml2/neutron/db/migration/models/__init__.py
apic_ml2/neutron/db/migration/models/head.py
apic_ml2/neutron/plugins/__init__.py
apic_ml2/neutron/plugins/ml2/__init__.py
apic_ml2/neutron/plugins/ml2/drivers/__init__.py
apic_ml2/neutron/plugins/ml2/drivers/cisco/__init__.py
apic_ml2/neutron/plugins/ml2/drivers/cisco/apic/__init__.py
apic_ml2/neutron/plugins/ml2/drivers/cisco/apic/apic_sync.py
apic_ml2/neutron/plugins/ml2/drivers/cisco/apic/apic_topology.py
apic_ml2/neutron/plugins/ml2/drivers/cisco/apic/attestation.py
apic_ml2/neutron/plugins/ml2/drivers/cisco/apic/config.py
apic_ml2/neutron/plugins/ml2/drivers/cisco/apic/mechanism_apic.py
apic_ml2/neutron/plugins/ml2/drivers/cisco/apic/nova_client.py
apic_ml2/neutron/plugins/ml2/drivers/cisco/apic/rpc.py
apic_ml2/neutron/services/__init__.py
apic_ml2/neutron/services/l3_router/__init__.py
neutron_ml2_driver_apic.egg-info/PKG-INFO
neutron_ml2_driver_apic.egg-info/SOURCES.txt
neutron_ml2_driver_apic.egg-info/dependency_links.txt
neutron_ml2_driver_apic.egg-info/entry_points.txt
neutron_ml2_driver_apic.egg-info/not-zip-safe
neutron_ml2_driver_apic.egg-info/pbr.json
neutron_ml2_driver_apic.egg-info/requires.txt
neutron_ml2_driver_apic.egg-info/top_level.txt
